django_admin_sticky_notes/__init__.py
django_admin_sticky_notes/models.py
django_admin_sticky_notes/urls.py
django_admin_sticky_notes/views.py
django_admin_sticky_notes/migrations/0001_initial.py
django_admin_sticky_notes/migrations/__init__.py
django_admin_sticky_notes/static/admin/css/note.css
django_admin_sticky_notes/static/admin/js/note.js
django_admin_sticky_notes/templates/admin/index.html
django_admin_sticky_notes-1.0.0.dist-info/METADATA
django_admin_sticky_notes-1.0.0.dist-info/WHEEL
django_admin_sticky_notes-1.0.0.dist-info/top_level.txt
django_admin_sticky_notes-1.0.0.dist-info/RECORD
